mcvqoe/audio_clips/__init__.py
mcvqoe/audio_clips/test.wav
mcvqoe/base/__init__.py
mcvqoe/base/audio_channels.py
mcvqoe/base/fsf.py
mcvqoe/base/measurement.py
mcvqoe/base/misc.py
mcvqoe/base/naming.py
mcvqoe/base/terminal_user.py
mcvqoe/base/version.py
mcvqoe/base/write_log.py
mcvqoe/delay/ITS_delay.py
mcvqoe/delay/__init__.py
mcvqoe/delay/sliding_delay.py
mcvqoe/diagnostics/__init__.py
mcvqoe/diagnostics/diagnostics.py
mcvqoe/diagnostics/diagnostics_eval.py
mcvqoe/gui/MCV-sm.png
mcvqoe/gui/__init__.py
mcvqoe/gui/test_info_gui.py
mcvqoe/hardware/PTT_play.py
mcvqoe/hardware/__init__.py
mcvqoe/hardware/audio_player.py
mcvqoe/hardware/radio_interface.py
mcvqoe/math/__init__.py
mcvqoe/math/resample_techniques.py
mcvqoe/simulation/Probabilityiser.py
mcvqoe/simulation/QoEsim.py
mcvqoe/simulation/__init__.py
mcvqoe/simulation/cleanchan.py
mcvqoe/simulation/pbiplugin.py
mcvqoe/timing/IRIGB_decode.py
mcvqoe/timing/__init__.py
mcvqoe/timing/audio_chans.py
mcvqoe/timing/soft_timecode.py
mcvqoe/timing/timecode.py
mcvqoe/timing/two_loc_process.py
mcvqoe/utilities/.gitignore
mcvqoe/utilities/README.md
mcvqoe/utilities/__init__.py
mcvqoe/utilities/channelinfo.py
mcvqoe/utilities/local_copy.py
mcvqoe/utilities/log_search.py
mcvqoe/utilities/reprocess.py
mcvqoe/utilities/sync.py
mcvqoe/utilities/test_copy.py
mcvqoe_base-1.3.2.dist-info/LICENSE.md
mcvqoe_base-1.3.2.dist-info/METADATA
mcvqoe_base-1.3.2.dist-info/WHEEL
mcvqoe_base-1.3.2.dist-info/entry_points.txt
mcvqoe_base-1.3.2.dist-info/top_level.txt
mcvqoe_base-1.3.2.dist-info/RECORD
