Metadata-Version: 2.2
Name: mcvqoe-base
Version: 1.3.2
Summary: Common code for MCV QoE Measurement Classes
Home-page: https://github.com/usnistgov/mcvqoe-base
Author: PSCR
Author-email: PSCR@PSCR.gov
License: NIST software License
Classifier: Programming Language :: Python :: 3
Classifier: License :: Public Domain
Classifier: Operating System :: OS Independent
Requires-Python: >=3.6
License-File: LICENSE.md
Requires-Dist: appdirs
Requires-Dist: importlib-metadata; python_version < "3.8"
Requires-Dist: numpy
Requires-Dist: pandas
Requires-Dist: plotly
Requires-Dist: pyserial
Requires-Dist: scipy
Requires-Dist: sounddevice
Requires-Dist: soundfile
Dynamic: author
Dynamic: author-email
Dynamic: classifier
Dynamic: description
Dynamic: description-content-type
Dynamic: home-page
Dynamic: license
Dynamic: requires-dist
Dynamic: requires-python
Dynamic: summary
